data_migrator/__init__.py
data_migrator/exceptions.py
data_migrator/transform.py
data_migrator/anonymizors/__init__.py
data_migrator/anonymizors/base.py
data_migrator/anonymizors/lists.py
data_migrator/anonymizors/strings.py
data_migrator/contrib/__init__.py
data_migrator/contrib/dutch.py
data_migrator/contrib/kinesis.py
data_migrator/contrib/read.py
data_migrator/emitters/__init__.py
data_migrator/emitters/base.py
data_migrator/emitters/csv.py
data_migrator/emitters/json_emit.py
data_migrator/emitters/mysql.py
data_migrator/emitters/singer.py
data_migrator/emitters/update.py
data_migrator/models/__init__.py
data_migrator/models/base.py
data_migrator/models/fields.py
data_migrator/models/manager.py
data_migrator/models/options.py
data_migrator/utils/__init__.py
data_migrator/utils/argparser.py
data_migrator/utils/compat.py
data_migrator/utils/csv.py
data_migrator/utils/log.py
data_migrator/utils/sql.py
data_migrator-0.6.2.dist-info/DESCRIPTION.rst
data_migrator-0.6.2.dist-info/LICENSE.txt
data_migrator-0.6.2.dist-info/METADATA
data_migrator-0.6.2.dist-info/RECORD
data_migrator-0.6.2.dist-info/WHEEL
data_migrator-0.6.2.dist-info/metadata.json
data_migrator-0.6.2.dist-info/top_level.txt
data_migrator-0.6.2.dist-info/zip-safe
