Metadata-Version: 2.0
Name: data-migrator
Version: 0.6.2
Summary: declarative data migration and transformation package
Home-page: https://github.com/schubergphilis/data-migrator
Author: Ilja Heitlager
Author-email: iheitlager@schubergphilis.com
License: MIT
Keywords: datamigration,development-tools
Platform: any
Classifier: Development Status :: 5 - Production/Stable
Classifier: Environment :: Console
Classifier: Topic :: Software Development :: Build Tools
Classifier: Topic :: Database
Classifier: Topic :: Utilities
Classifier: Operating System :: OS Independent
Classifier: Programming Language :: Python
Classifier: Programming Language :: Python :: 2.7
Classifier: Programming Language :: Python :: 3.6
Classifier: Intended Audience :: Developers
Classifier: License :: OSI Approved :: MIT License
Classifier: Natural Language :: English
Requires-Dist: boto3
Requires-Dist: python-dateutil
Requires-Dist: six
